{
  "de_cascaded_reports": {
    "committed_report_contracts": {
      "pr06910": {
        "report_path": "execution/reports/pr06910-portability-environment-report.json",
        "unit_tests_absent": true
      },
      "pr06911": {
        "comparison_fields_present": true,
        "hash_fields_absent": true,
        "report_path": "execution/reports/pr06911-glue-script-safety-report.json",
        "unit_tests_absent": true
      },
      "pr06913": {
        "comparison_fields_present": true,
        "hash_fields_absent": true,
        "report_path": "execution/reports/pr06913-documentation-architecture-clarity-report.json"
      }
    }
  },
  "deterministic": true,
  "emitted_concurrency_evidence": {
    "compile": {
      "command": [
        "alr",
        "exec",
        "--",
        "gprbuild",
        "-c",
        "-P",
        "$TMPDIR/ada/build.gpr",
        "select_with_delay_multiarm.adb",
        "-cargs",
        "-gnatec=$TMPDIR/ada/gnat.adc"
      ],
      "cwd": "$REPO_ROOT/compiler_impl",
      "returncode": 0
    },
    "fixture": "tests/concurrency/select_with_delay_multiarm.safe",
    "flow": {
      "command": [
        "alr",
        "exec",
        "--",
        "gnatprove",
        "-P",
        "$TMPDIR/ada/build.gpr",
        "--mode=flow",
        "--report=all",
        "--warnings=error",
        "-cargs",
        "-gnatec=$TMPDIR/ada/gnat.adc"
      ],
      "cwd": "$REPO_ROOT/compiler_impl",
      "returncode": 0,
      "summary": {
        "rows": {
          "Assertions": {
            "flow": {
              "count": 0,
              "detail": ""
            },
            "justified": {
              "count": 0,
              "detail": ""
            },
            "provers": {
              "count": 0,
              "detail": ""
            },
            "total": {
              "count": 0,
              "detail": ""
            },
            "unproved": {
              "count": 0,
              "detail": ""
            }
          },
          "Concurrency": {
            "flow": {
              "count": 0,
              "detail": ""
            },
            "justified": {
              "count": 0,
              "detail": ""
            },
            "provers": {
              "count": 0,
              "detail": ""
            },
            "total": {
              "count": 0,
              "detail": ""
            },
            "unproved": {
              "count": 0,
              "detail": ""
            }
          },
          "Data Dependencies": {
            "flow": {
              "count": 0,
              "detail": ""
            },
            "justified": {
              "count": 0,
              "detail": ""
            },
            "provers": {
              "count": 0,
              "detail": ""
            },
            "total": {
              "count": 0,
              "detail": ""
            },
            "unproved": {
              "count": 0,
              "detail": ""
            }
          },
          "Flow Dependencies": {
            "flow": {
              "count": 1,
              "detail": ""
            },
            "justified": {
              "count": 0,
              "detail": ""
            },
            "provers": {
              "count": 0,
              "detail": ""
            },
            "total": {
              "count": 1,
              "detail": ""
            },
            "unproved": {
              "count": 0,
              "detail": ""
            }
          },
          "Functional Contracts": {
            "flow": {
              "count": 0,
              "detail": ""
            },
            "justified": {
              "count": 0,
              "detail": ""
            },
            "provers": {
              "count": 0,
              "detail": ""
            },
            "total": {
              "count": 0,
              "detail": ""
            },
            "unproved": {
              "count": 0,
              "detail": ""
            }
          },
          "Initialization": {
            "flow": {
              "count": 10,
              "detail": ""
            },
            "justified": {
              "count": 0,
              "detail": ""
            },
            "provers": {
              "count": 0,
              "detail": ""
            },
            "total": {
              "count": 10,
              "detail": ""
            },
            "unproved": {
              "count": 0,
              "detail": ""
            }
          },
          "LSP Verification": {
            "flow": {
              "count": 0,
              "detail": ""
            },
            "justified": {
              "count": 0,
              "detail": ""
            },
            "provers": {
              "count": 0,
              "detail": ""
            },
            "total": {
              "count": 0,
              "detail": ""
            },
            "unproved": {
              "count": 0,
              "detail": ""
            }
          },
          "Non-Aliasing": {
            "flow": {
              "count": 0,
              "detail": ""
            },
            "justified": {
              "count": 0,
              "detail": ""
            },
            "provers": {
              "count": 0,
              "detail": ""
            },
            "total": {
              "count": 0,
              "detail": ""
            },
            "unproved": {
              "count": 0,
              "detail": ""
            }
          },
          "Run-time Checks": {
            "flow": {
              "count": 0,
              "detail": ""
            },
            "justified": {
              "count": 0,
              "detail": ""
            },
            "provers": {
              "count": 0,
              "detail": ""
            },
            "total": {
              "count": 0,
              "detail": ""
            },
            "unproved": {
              "count": 0,
              "detail": ""
            }
          },
          "Termination": {
            "flow": {
              "count": 0,
              "detail": ""
            },
            "justified": {
              "count": 0,
              "detail": ""
            },
            "provers": {
              "count": 0,
              "detail": ""
            },
            "total": {
              "count": 0,
              "detail": ""
            },
            "unproved": {
              "count": 0,
              "detail": ""
            }
          },
          "Total": {
            "flow": {
              "count": 11,
              "detail": "100%"
            },
            "justified": {
              "count": 0,
              "detail": ""
            },
            "provers": {
              "count": 0,
              "detail": ""
            },
            "total": {
              "count": 11,
              "detail": ""
            },
            "unproved": {
              "count": 0,
              "detail": ""
            }
          }
        },
        "total": {
          "flow": {
            "count": 11,
            "detail": "100%"
          },
          "justified": {
            "count": 0,
            "detail": ""
          },
          "provers": {
            "count": 0,
            "detail": ""
          },
          "total": {
            "count": 11,
            "detail": ""
          },
          "unproved": {
            "count": 0,
            "detail": ""
          }
        }
      }
    },
    "prove": {
      "command": [
        "alr",
        "exec",
        "--",
        "gnatprove",
        "-P",
        "$TMPDIR/ada/build.gpr",
        "--mode=prove",
        "--level=2",
        "--prover=cvc5,z3,altergo",
        "--steps=0",
        "--timeout=120",
        "--report=all",
        "--warnings=error",
        "--checks-as-errors=on",
        "-cargs",
        "-gnatec=$TMPDIR/ada/gnat.adc"
      ],
      "cwd": "$REPO_ROOT/compiler_impl",
      "returncode": 0,
      "summary": {
        "rows": {
          "Assertions": {
            "flow": {
              "count": 0,
              "detail": ""
            },
            "justified": {
              "count": 0,
              "detail": ""
            },
            "provers": {
              "count": 0,
              "detail": ""
            },
            "total": {
              "count": 0,
              "detail": ""
            },
            "unproved": {
              "count": 0,
              "detail": ""
            }
          },
          "Concurrency": {
            "flow": {
              "count": 0,
              "detail": ""
            },
            "justified": {
              "count": 0,
              "detail": ""
            },
            "provers": {
              "count": 0,
              "detail": ""
            },
            "total": {
              "count": 0,
              "detail": ""
            },
            "unproved": {
              "count": 0,
              "detail": ""
            }
          },
          "Data Dependencies": {
            "flow": {
              "count": 0,
              "detail": ""
            },
            "justified": {
              "count": 0,
              "detail": ""
            },
            "provers": {
              "count": 0,
              "detail": ""
            },
            "total": {
              "count": 0,
              "detail": ""
            },
            "unproved": {
              "count": 0,
              "detail": ""
            }
          },
          "Flow Dependencies": {
            "flow": {
              "count": 1,
              "detail": ""
            },
            "justified": {
              "count": 0,
              "detail": ""
            },
            "provers": {
              "count": 0,
              "detail": ""
            },
            "total": {
              "count": 1,
              "detail": ""
            },
            "unproved": {
              "count": 0,
              "detail": ""
            }
          },
          "Functional Contracts": {
            "flow": {
              "count": 0,
              "detail": ""
            },
            "justified": {
              "count": 0,
              "detail": ""
            },
            "provers": {
              "count": 0,
              "detail": ""
            },
            "total": {
              "count": 0,
              "detail": ""
            },
            "unproved": {
              "count": 0,
              "detail": ""
            }
          },
          "Initialization": {
            "flow": {
              "count": 10,
              "detail": ""
            },
            "justified": {
              "count": 0,
              "detail": ""
            },
            "provers": {
              "count": 0,
              "detail": ""
            },
            "total": {
              "count": 10,
              "detail": ""
            },
            "unproved": {
              "count": 0,
              "detail": ""
            }
          },
          "LSP Verification": {
            "flow": {
              "count": 0,
              "detail": ""
            },
            "justified": {
              "count": 0,
              "detail": ""
            },
            "provers": {
              "count": 0,
              "detail": ""
            },
            "total": {
              "count": 0,
              "detail": ""
            },
            "unproved": {
              "count": 0,
              "detail": ""
            }
          },
          "Non-Aliasing": {
            "flow": {
              "count": 0,
              "detail": ""
            },
            "justified": {
              "count": 0,
              "detail": ""
            },
            "provers": {
              "count": 0,
              "detail": ""
            },
            "total": {
              "count": 0,
              "detail": ""
            },
            "unproved": {
              "count": 0,
              "detail": ""
            }
          },
          "Run-time Checks": {
            "flow": {
              "count": 0,
              "detail": ""
            },
            "justified": {
              "count": 0,
              "detail": ""
            },
            "provers": {
              "count": 32,
              "detail": "CVC5"
            },
            "total": {
              "count": 32,
              "detail": ""
            },
            "unproved": {
              "count": 0,
              "detail": ""
            }
          },
          "Termination": {
            "flow": {
              "count": 0,
              "detail": ""
            },
            "justified": {
              "count": 0,
              "detail": ""
            },
            "provers": {
              "count": 0,
              "detail": ""
            },
            "total": {
              "count": 0,
              "detail": ""
            },
            "unproved": {
              "count": 0,
              "detail": ""
            }
          },
          "Total": {
            "flow": {
              "count": 11,
              "detail": "26%"
            },
            "justified": {
              "count": 0,
              "detail": ""
            },
            "provers": {
              "count": 32,
              "detail": "74%"
            },
            "total": {
              "count": 43,
              "detail": ""
            },
            "unproved": {
              "count": 0,
              "detail": ""
            }
          }
        },
        "total": {
          "flow": {
            "count": 11,
            "detail": "26%"
          },
          "justified": {
            "count": 0,
            "detail": ""
          },
          "provers": {
            "count": 32,
            "detail": "74%"
          },
          "total": {
            "count": 43,
            "detail": ""
          },
          "unproved": {
            "count": 0,
            "detail": ""
          }
        }
      }
    },
    "prove_profile": {
      "actual_command": [
        "alr",
        "exec",
        "--",
        "gnatprove",
        "-P",
        "$TMPDIR/ada/build.gpr",
        "--mode=prove",
        "--level=2",
        "--prover=cvc5,z3,altergo",
        "--steps=0",
        "--timeout=120",
        "--report=all",
        "--warnings=error",
        "--checks-as-errors=on",
        "-cargs",
        "-gnatec=$TMPDIR/ada/gnat.adc"
      ],
      "shared_switches": [
        "--mode=prove",
        "--level=2",
        "--prover=cvc5,z3,altergo",
        "--steps=0",
        "--timeout=120",
        "--report=all",
        "--warnings=error",
        "--checks-as-errors=on"
      ]
    }
  },
  "gnatprove_profile_doc": {
    "path": "docs/gnatprove_profile.md",
    "required_snippets": [
      "### 4.7 Emitted-Proof Reproducibility Contract",
      "`--mode=prove --level=2 --prover=cvc5,z3,altergo --steps=0 --timeout=120 --report=all --warnings=error --checks-as-errors=on`",
      "deterministic reports plus normalized GNATprove summaries",
      "GNATprove session artifacts are not committed and are not part of the reproducibility contract"
    ]
  },
  "parser_regressions": {
    "command": [
      "python3",
      "-m",
      "unittest",
      "scripts.tests.test_pr101_audit_hardening"
    ],
    "cwd": "$REPO_ROOT",
    "returncode": 0
  },
  "repeat_sha256": "ef485bc73ed9d944216a4805063ed858ec056636e50af6d963cd5d295252c8c5",
  "report_sha256": "ef485bc73ed9d944216a4805063ed858ec056636e50af6d963cd5d295252c8c5",
  "status": "ok",
  "task": "PR10.4"
}
